{
  "parent": "minecraft:recipes/root",
  "rewards": {
    "recipes": [
      "butchercraft:cooked_cow_kidney_from_campfire_cooking"
    ]
  },
  "criteria": {
    "has_cow_kidney": {
      "trigger": "minecraft:inventory_changed",
      "conditions": {
        "items": [
          {
            "items": [
              "butchercraft:cow_kidney"
            ]
          }
        ]
      }
    },
    "has_the_recipe": {
      "trigger": "minecraft:recipe_unlocked",
      "conditions": {
        "recipe": "butchercraft:cooked_cow_kidney_from_campfire_cooking"
      }
    }
  },
  "requirements": [
    [
      "has_cow_kidney",
      "has_the_recipe"
    ]
  ]
}