{
  "type": "butchercraft:meat_hook",
  "group": "",
  "tools": [
    {
      "uses": 6,
      "tool": {
        "item": "butchercraft:skinning_knife"
      },
      "count": 1,
      "damage": true,
      "loot_table": "butchercraft:recipes/meat_hook/cow",
      "models": [
        {
          "location": "minecraft:diamond_sword",
          "animation": {
            "location": {},
            "rotation": {
              "y": {
                "max": 360.0,
                "speed": 0.1,
                "loop": true
              }
            },
            "scale": {}
          }
        }
      ]
    }
  ],
  "carcass": {
    "item": "butchercraft:cow_carcass"
  }
}