{
  "type": "farmersdelight:cooking",
  "ingredients": [
    {
      "item": "minecraft:potato"
    },
    {
      "item": "minecraft:potato"
    },
    {
      "item": "minecraft:potato"
    },
    {
      "item": "minecraft:potato"
    },
    {
      "item": "butchercraft:gravy_boat_item"
    },
    {
      "item": "minecraft:milk_bucket"
    }
  ],
  "result": {
    "item": "butchercraft:mashed_potato_gravy_block_item"
  },
  "container": {
    "item": "minecraft:bowl"
  },
  "experience": 0.35,
  "cookingtime": 400
}